[
  {
    "link": "https://www.vinted.fr/items/5591993186-legor-piece-detachee-autocollee-set-43231",
    "price": "1.75",
    "title": "Lego® - Pièce détachée autocollée : set 43231",
    "published": "03/01/2025 09:48:49",
    "status": "Très bon état"
  },
  {
    "link": "https://www.vinted.fr/items/5893372279-lego-disney",
    "price": "16.45",
    "title": "Lego Disney",
    "published": "28/02/2025 22:59:34",
    "status": "Très bon état"
  },
  {
    "link": "https://www.vinted.fr/items/5880278568-lego-disney-43231-cottage-dasha",
    "price": "35.35",
    "title": "Lego disney 43231 cottage d’asha",
    "published": "26/02/2025 12:13:49",
    "status": "Neuf avec étiquette"
  },
  {
    "link": "https://www.vinted.fr/items/5826247725-set-43231-lego-disney",
    "price": "32.2",
    "title": "Set 43231 Lego Disney",
    "published": "16/02/2025 15:51:41",
    "status": "Neuf sans étiquette"
  },
  {
    "link": "https://www.vinted.fr/items/5945583238-lego-disney-43231",
    "price": "42.7",
    "title": "Lego Disney 43231",
    "published": "10/03/2025 15:23:24",
    "status": "Très bon état"
  },
  {
    "link": "https://www.vinted.fr/items/5811856292-lego-43231-disney-wish-il-cottage-di-asha",
    "price": "39.55",
    "title": "Lego 43231 Disney Wish Il Cottage di Asha",
    "published": "13/02/2025 18:22:05",
    "status": "Neuf avec étiquette"
  },
  {
    "link": "https://www.vinted.fr/items/5799040058-lego-disney-43231-ashas-cottage",
    "price": "37.98",
    "title": "Lego Disney 43231 Asha's Cottage",
    "published": "11/02/2025 10:02:51",
    "status": "Neuf sans étiquette"
  },
  {
    "link": "https://www.vinted.fr/items/5621165944-lego-43231-disney-wish-nuovo",
    "price": "38.5",
    "title": "Lego 43231 Disney Wish nuovo",
    "published": "08/01/2025 15:29:29",
    "status": "Neuf avec étiquette"
  },
  {
    "link": "https://www.vinted.fr/items/5503740533-43231-lego-disney-wish-ashas-cottage",
    "price": "41.65",
    "title": "43231 LEGO - Disney Wish Asha's Cottage",
    "published": "09/12/2024 07:02:51",
    "status": "Neuf avec étiquette"
  },
  {
    "link": "https://www.vinted.fr/items/5606148062-creator-la-chaumiere-dasha-43231",
    "price": "21.7",
    "title": "Creator la chaumière d'Asha 43231",
    "published": "05/01/2025 16:20:45",
    "status": "Très bon état"
  },
  {
    "link": "https://www.vinted.fr/items/5684328105-lego-disney-wish-43231",
    "price": "53.2",
    "title": "Lego disney wish 43231",
    "published": "20/01/2025 16:08:21",
    "status": "Très bon état"
  },
  {
    "link": "https://www.vinted.fr/items/5151717162-lego-ref-43231-disney-wish-new-in-box",
    "price": "40.6",
    "title": "LEGO -  (Ref 43231) - Disney Wish - New in Box",
    "published": "03/10/2024 15:09:48",
    "status": "Neuf avec étiquette"
  },
  {
    "link": "https://www.vinted.fr/items/5720514574-lego-disney-43231-ashas-hauschen-neu",
    "price": "39.55",
    "title": "Lego Disney 43231 Ashas Häuschen - Neu",
    "published": "27/01/2025 13:37:10",
    "status": "Neuf avec étiquette"
  },
  {
    "link": "https://www.vinted.fr/items/5661248579-lego-disney-ashas-cottage-43231",
    "price": "35.34",
    "title": "Lego Disney Asha's Cottage (43231",
    "published": "16/01/2025 13:03:07",
    "status": "Neuf avec étiquette"
  },
  {
    "link": "https://www.vinted.fr/items/5793971613-legos-casa-de-campo-da-asha-novo",
    "price": "39.55",
    "title": "Legos- Casa de Campo da Asha ( novo)",
    "published": "10/02/2025 10:54:01",
    "status": "Neuf avec étiquette"
  },
  {
    "link": "https://www.vinted.fr/items/5782758749-lego-disney-la-chaumiere-dasha-43231-neuf",
    "price": "53.2",
    "title": "LEGO Disney La chaumière d'Asha 43231 Neuf",
    "published": "08/02/2025 14:54:15",
    "status": "Neuf avec étiquette"
  },
  {
    "link": "https://www.vinted.fr/items/5433152347-lego-disney-wish-il-cottage-di-asha-43231",
    "price": "47.95",
    "title": "Lego Disney Wish Il Cottage di Asha 43231",
    "published": "24/11/2024 12:07:01",
    "status": "Neuf avec étiquette"
  },
  {
    "link": "https://www.vinted.fr/items/4526272323-mlp-2014-honey-ray",
    "price": "7.0",
    "title": "MLP 2014 Honey Ray",
    "published": "19/05/2024 19:09:59",
    "status": "Bon état"
  },
  {
    "link": "https://www.vinted.fr/items/5780333908-lego-43231-cottage-di-asha",
    "price": "41.65",
    "title": "Lego 43231 cottage di Asha",
    "published": "08/02/2025 06:59:35",
    "status": "Neuf sans étiquette"
  },
  {
    "link": "https://www.vinted.fr/items/4170142702-lego-disney-wish-43231-7",
    "price": "47.95",
    "title": "Lego Disney Wish 43231 7+",
    "published": "02/03/2024 12:26:51",
    "status": "Neuf avec étiquette"
  },
  {
    "link": "https://www.vinted.fr/items/5572136675-lego-43231-cottage-di-asha",
    "price": "56.35",
    "title": "Lego 43231 Cottage di Asha",
    "published": "29/12/2024 11:45:06",
    "status": "Neuf avec étiquette"
  },
  {
    "link": "https://www.vinted.fr/items/5559965547-blind-guardian-follow-the-blind-1989",
    "price": "42.7",
    "title": "Blind Guardian - Follow The Blind 1989",
    "published": "25/12/2024 18:46:53",
    "status": "Neuf avec étiquette"
  },
  {
    "link": "https://www.vinted.fr/items/5846433885-lego-43231-disney-wish-ashas-hauschen",
    "price": "46.9",
    "title": "LEGO 43231 Disney Wish Ashas Häuschen",
    "published": "20/02/2025 10:37:03",
    "status": "Neuf avec étiquette"
  },
  {
    "link": "https://www.vinted.fr/items/5545572484-lego-disney-43231-ashas-cottage",
    "price": "47.94",
    "title": "Lego Disney 43231 Asha’s Cottage.",
    "published": "19/12/2024 20:34:59",
    "status": "Neuf sans étiquette"
  },
  {
    "link": "https://www.vinted.fr/items/5555044630-lego-disney-wish-kasteel-van-koning-magnifico-wish-film-set-43224",
    "price": "53.15",
    "title": "LEGO Disney Wish Kasteel van koning Magnifico Wish Film Set - 43224",
    "published": "23/12/2024 08:57:07",
    "status": "Neuf sans étiquette"
  },
  {
    "link": "https://www.vinted.fr/items/5621198342-nr-2-pz-disney-wish-nuovi",
    "price": "56.35",
    "title": "Nr. 2 pz Disney Wish nuovi !",
    "published": "08/01/2025 15:34:05",
    "status": "Neuf avec étiquette"
  },
  {
    "link": "https://www.vinted.fr/items/4515088070-mini-pony-hasbro-2010",
    "price": "5.85",
    "title": "Mini pony hasbro 2010",
    "published": "17/05/2024 13:13:56",
    "status": "Très bon état"
  },
  {
    "link": "https://www.vinted.fr/items/4489121217-balance-of-power-boargame",
    "price": "26.95",
    "title": "Balance of Power boargame",
    "published": "11/05/2024 17:39:11",
    "status": "Neuf sans étiquette"
  },
  {
    "link": "https://www.vinted.fr/items/5484565707-lego-disney-43224-le-chateau-du-roi-magnifico",
    "price": "95.2",
    "title": "Lego DISNEY 43224 : Le château du roi Magnifico",
    "published": "04/12/2024 21:29:26",
    "status": "Neuf avec étiquette"
  }
]